sorting_api/__init__.py
sorting_api/__main__.py
sorting_api/main.py
sorting_api/routing/__init__.py
sorting_api/routing/router.py
sorting_api/routing/endpoints/__init__.py
sorting_api/routing/endpoints/random.py
sorting_api/routing/endpoints/sort.py
sorting_api/static/__init__.py
sorting_api/static/sorting_algo.py
sorting_api/utils/__init__.py
sorting_api/utils/body_validation.py
SortingAPI-0.0.4.dist-info/METADATA
SortingAPI-0.0.4.dist-info/WHEEL
SortingAPI-0.0.4.dist-info/entry_points.txt
SortingAPI-0.0.4.dist-info/top_level.txt
SortingAPI-0.0.4.dist-info/RECORD
