Metadata-Version: 2.1
Name: SortingAPI
Version: 0.0.4
Author: Andrea Broccoletti, Simone Lesinigo
Requires-Dist: uvicorn
Requires-Dist: fastapi
Requires-Dist: pysort
